data_engineering_job_market_package_FelitaD/__init__.py
data_engineering_job_market_package_FelitaD/config/__init__.py
data_engineering_job_market_package_FelitaD/config/definitions.py
data_engineering_job_market_package_FelitaD/config/postgres_schema.py
data_engineering_job_market_package_FelitaD/elt/__init__.py
data_engineering_job_market_package_FelitaD/elt/transform_and_load.py
data_engineering_job_market_package_FelitaD/elt/extract/__init__.py
data_engineering_job_market_package_FelitaD/elt/extract/jobs_crawler/__init__.py
data_engineering_job_market_package_FelitaD/elt/extract/jobs_crawler/items.py
data_engineering_job_market_package_FelitaD/elt/extract/jobs_crawler/middlewares.py
data_engineering_job_market_package_FelitaD/elt/extract/jobs_crawler/pipelines.py
data_engineering_job_market_package_FelitaD/elt/extract/jobs_crawler/settings.py
data_engineering_job_market_package_FelitaD/elt/extract/jobs_crawler/spiders/__init__.py
data_engineering_job_market_package_FelitaD/elt/extract/jobs_crawler/spiders/spotify.py
data_engineering_job_market_package_FelitaD/elt/extract/jobs_crawler/spiders/spotify_links.py
data_engineering_job_market_package_FelitaD/elt/extract/jobs_crawler/spiders/wttj.py
data_engineering_job_market_package_FelitaD/elt/extract/jobs_crawler/spiders/wttj_links.py
data_engineering_job_market_package_FelitaD/elt/load/create_tables.py
data_engineering_job_market_package_FelitaD/elt/load/load.py
data_engineering_job_market_package_FelitaD/elt/transform/preprocess.py
data_engineering_job_market_package_FelitaD/elt/transform/process_technos.py
data_engineering_job_market_package_FelitaD/elt/transform/transform.py
data_engineering_job_market_package_FelitaD/elt/transform/ner_technos/ner_preprocessor.py
data_engineering_job_market_package_FelitaD/elt/transform/ner_technos/train_model.py
data_engineering_job_market-0.1.4.dist-info/METADATA
data_engineering_job_market-0.1.4.dist-info/WHEEL
data_engineering_job_market-0.1.4.dist-info/top_level.txt
data_engineering_job_market-0.1.4.dist-info/RECORD
