Metadata-Version: 2.1
Name: data-engineering-job-market
Version: 0.1.4
Summary: A data engineering batch pipeline to analyse job postings.
Author-email: Félita Donor <donorfelita@msn.com>
Project-URL: Homepage, https://github.com/FelitaD/data_engineering_job_market
Project-URL: Bug Tracker, https://github.com/FelitaD/data_engineering_job_market/issues
Classifier: Programming Language :: Python :: 3
Classifier: Operating System :: OS Independent
Requires-Python: >=3.7
Requires-Dist: pandas
Requires-Dist: psycopg2
Requires-Dist: playwright
Requires-Dist: scrapy
